MANIFEST.in
setup.py
previewr/__init__.py
previewr/processors.py
previewr/server.py
previewr/utils.py
previewr.egg-info/PKG-INFO
previewr.egg-info/SOURCES.txt
previewr.egg-info/dependency_links.txt
previewr.egg-info/entry_points.txt
previewr.egg-info/requires.txt
previewr.egg-info/top_level.txt
previewr.egg-info/zip-safe
previewr/static/favicon.ico
previewr/static/github.css
previewr/static/jquery.min.js
previewr/static/mistype.css
previewr/static/specific.css
previewr/static/toc.jquery.min.js
previewr/static/update.js
previewr/templates/index.html