Metadata-Version: 1.1
Name: previewr
Version: 0.4.0
Summary: Simple Markdown/reStructured Text previewer
Home-page: http://raphael.li/projects/previewr/
Author: Raphael Zimmermann
Author-email: mister.norbert@gmail.com
License: MIT
Platform: UNKNOWN
Classifier: Programming Language :: Python :: 3
Classifier: Development Status :: 4 - Beta
Classifier: Intended Audience :: Developers
Classifier: License :: OSI Approved :: MIT License
Classifier: Operating System :: OS Independent
Classifier: Topic :: Software Development :: Libraries :: Python Modules
Classifier: Topic :: Text Processing :: Linguistic
